django_jwt_extended/__init__.py
django_jwt_extended/apps.py
django_jwt_extended/config.py
django_jwt_extended/decorators.py
django_jwt_extended/exceptions.py
django_jwt_extended/request.py
django_jwt_extended/tokens.py
django_jwt_extended-2.0.0.dist-info/LICENSE.md
django_jwt_extended-2.0.0.dist-info/METADATA
django_jwt_extended-2.0.0.dist-info/WHEEL
django_jwt_extended-2.0.0.dist-info/top_level.txt
django_jwt_extended-2.0.0.dist-info/RECORD
